FlaskDaxingJiaocheng/README.md
FlaskDaxingJiaocheng/__init__.py
FlaskDaxingJiaocheng/__main__.py
FlaskDaxingJiaocheng/file.epub
FlaskDaxingJiaocheng/index.html
FlaskDaxingJiaocheng/css/__init__.py
FlaskDaxingJiaocheng/css/annotations.css
FlaskDaxingJiaocheng/css/main.css
FlaskDaxingJiaocheng/css/normalize.css
FlaskDaxingJiaocheng/css/popup.css
FlaskDaxingJiaocheng/font/__init__.py
FlaskDaxingJiaocheng/font/fontello.eot
FlaskDaxingJiaocheng/font/fontello.svg
FlaskDaxingJiaocheng/font/fontello.ttf
FlaskDaxingJiaocheng/font/fontello.woff
FlaskDaxingJiaocheng/img/__init__.py
FlaskDaxingJiaocheng/img/annotator-glyph-sprite.png
FlaskDaxingJiaocheng/img/annotator-icon-sprite.png
FlaskDaxingJiaocheng/img/apple-touch-icon.png
FlaskDaxingJiaocheng/img/cancelfullscreen.png
FlaskDaxingJiaocheng/img/close.png
FlaskDaxingJiaocheng/img/fullscreen.png
FlaskDaxingJiaocheng/img/loader.gif
FlaskDaxingJiaocheng/img/menu-icon.png
FlaskDaxingJiaocheng/img/save.png
FlaskDaxingJiaocheng/img/saved.png
FlaskDaxingJiaocheng/img/settings-s.png
FlaskDaxingJiaocheng/img/settings.png
FlaskDaxingJiaocheng/img/star.png
FlaskDaxingJiaocheng/js/__init__.py
FlaskDaxingJiaocheng/js/epub.js
FlaskDaxingJiaocheng/js/epub.min.js
FlaskDaxingJiaocheng/js/epub.min.map
FlaskDaxingJiaocheng/js/hooks.min.js
FlaskDaxingJiaocheng/js/hooks.min.map
FlaskDaxingJiaocheng/js/reader.js
FlaskDaxingJiaocheng/js/reader.js.map
FlaskDaxingJiaocheng/js/reader.min.js
FlaskDaxingJiaocheng/js/reader.min.map
FlaskDaxingJiaocheng/js/hooks/__init__.py
FlaskDaxingJiaocheng/js/hooks/extensions/__init__.py
FlaskDaxingJiaocheng/js/hooks/extensions/highlight.js
FlaskDaxingJiaocheng/js/libs/__init__.py
FlaskDaxingJiaocheng/js/libs/jquery.min.js
FlaskDaxingJiaocheng/js/libs/localforage.min.js
FlaskDaxingJiaocheng/js/libs/screenfull.js
FlaskDaxingJiaocheng/js/libs/screenfull.min.js
FlaskDaxingJiaocheng/js/libs/zip.min.js
FlaskDaxingJiaocheng/js/plugins/__init__.py
FlaskDaxingJiaocheng/js/plugins/hypothesis.js
flask_daxing_jiaocheng-2024.3.2.0.dist-info/METADATA
flask_daxing_jiaocheng-2024.3.2.0.dist-info/WHEEL
flask_daxing_jiaocheng-2024.3.2.0.dist-info/entry_points.txt
flask_daxing_jiaocheng-2024.3.2.0.dist-info/top_level.txt
flask_daxing_jiaocheng-2024.3.2.0.dist-info/RECORD
